pmix/__init__.py
pmix/__version__.py
pmix/analytics.py
pmix/borrow.py
pmix/cascade.py
pmix/numbering.py
pmix/renumber.py
pmix/verbiage.py
pmix/xlsdiff.py
pmix/error/__init__.py
pmix/spreadsheet/__init__.py
pmix/spreadsheet/cell.py
pmix/spreadsheet/wbformat.py
pmix/spreadsheet/workbook.py
pmix/spreadsheet/worksheet.py
pmix/spreadsheet/xlsform.py
pmix/spreadsheet/xlstab.py
pmix/utils/__init__.py
pmix-0.7.0.dist-info/LICENSE.txt
pmix-0.7.0.dist-info/METADATA
pmix-0.7.0.dist-info/WHEEL
pmix-0.7.0.dist-info/entry_points.txt
pmix-0.7.0.dist-info/top_level.txt
pmix-0.7.0.dist-info/RECORD
