Metadata-Version: 2.1
Name: pmix
Version: 0.7.0
Summary: A mixed bag of Python3 tools for PMA workflow
Home-page: https://github.com/pmaengineering/pmix
Author: James Pringle
Author-email: jpringle@jhu.edu
License: MIT
Platform: UNKNOWN
Classifier: License :: OSI Approved :: MIT License
Classifier: Programming Language :: Python
Classifier: Programming Language :: Python :: 3
Classifier: Programming Language :: Python :: 3.6
Classifier: Programming Language :: Python :: 3.7
Classifier: Programming Language :: Python :: 3.8
Classifier: Programming Language :: Python :: Implementation :: CPython
Classifier: Programming Language :: Python :: Implementation :: PyPy
Requires-Python: >=3.6.0
Requires-Dist: XlsxWriter (>=1.1.0)
Requires-Dist: xlrd (>=1.1.0)
